auralib/__init__.py
auralib/cmd.py
auralib/config.py
auralib/files.py
auralib/json.py
auralib/skyrim.py
auralib/type.py
auralib/xml.py
auralib-0.0.4.dist-info/LICENSE.txt
auralib-0.0.4.dist-info/METADATA
auralib-0.0.4.dist-info/WHEEL
auralib-0.0.4.dist-info/top_level.txt
auralib-0.0.4.dist-info/RECORD
