Metadata-Version: 2.1
Name: auralib
Version: 0.0.4
Summary: Various functions to simplify common tasks
Author: GroundAura
Author-email: <groundaura@gmail.com>
License: Clear BSD
Classifier: Development Status :: 1 - Planning
Classifier: Intended Audience :: Developers
Classifier: Programming Language :: Python :: 3
License-File: LICENSE.txt
